{
    "display": {
        "title": "Cryo-Bomb                                                                                     ",
        "description": ["",
            {"text":"Place blue ice on a magma block to create a Cryo-Bomb.","color":"green"},{"text":"\n"},
            {"text":"Placing Packed Ice next to magma will create a Mini Cryo-Bomb","color":"dark_green"}
            ],
        "icon": {
            "item": "minecraft:blue_ice"
        },
        "announce_to_chat": false,
        "show_toast": false
    },
    "parent": "inhauspacks:thermodynamic",
    "criteria": {
        "trigger": {
            "trigger": "minecraft:tick"
        }
    }
}